nessai_gw/__init__.py
nessai_gw/proposals.py
nessai_gw/reparameterisations/__init__.py
nessai_gw/reparameterisations/distance.py
nessai_gw/reparameterisations/distance_converters.py
nessai_gw/reparameterisations/phase.py
nessai_gw/reparameterisations/utils.py
nessai_gw-0.1.0.dist-info/LICENSE
nessai_gw-0.1.0.dist-info/METADATA
nessai_gw-0.1.0.dist-info/WHEEL
nessai_gw-0.1.0.dist-info/entry_points.txt
nessai_gw-0.1.0.dist-info/top_level.txt
nessai_gw-0.1.0.dist-info/RECORD
